.gitignore
.travis.yml
AUTHORS
CONTRIBUTING.md
CONTRIBUTORS
LICENSE
README.md
requirements.txt
setup.py
tox.ini
micromanager/__init__.py
micromanager/exceptions.py
micromanager/micromanager.py
micromanager.egg-info/PKG-INFO
micromanager.egg-info/SOURCES.txt
micromanager.egg-info/dependency_links.txt
micromanager.egg-info/requires.txt
micromanager.egg-info/top_level.txt
micromanager/engines/__init__.py
micromanager/engines/opa.py
micromanager/engines/python.py
micromanager/resources/__init__.py
micromanager/resources/__init__.pyc
micromanager/resources/base.py
micromanager/resources/gcp.py
policy/config.yaml
policy/exclusions.rego
policy/policies.rego
policy/bigquery/common.rego
policy/bigquery/dataset_no_public_access.rego
policy/bigquery/dataset_no_public_access_test.rego
policy/bigquery/dataset_no_public_authenticated_access.rego
policy/bigquery/dataset_no_public_authenticated_access_test.rego
policy/cloudresourcemanager/cloudsql_data_access_logging.rego
policy/cloudresourcemanager/common_iam.rego
policy/cloudresourcemanager/storage_data_access_logging.rego
policy/sql/acl.rego
policy/sql/acl_test.rego
policy/sql/backups.rego
policy/sql/backups_test.rego
policy/sql/common.rego
policy/sql/require_ssl.rego
policy/sql/require_ssl_test.rego
policy/storage/bucket_iam_disallow_allauthenticatedusers.rego
policy/storage/bucket_iam_disallow_allauthenticatedusers_test.rego
policy/storage/bucket_iam_disallow_allusers.rego
policy/storage/bucket_iam_disallow_allusers_test.rego
policy/storage/common.rego
policy/storage/common_iam.rego
policy/storage/versioning.rego
policy/storage/versioning_test.rego
tests/__init__.py
tests/test_resources.py
tests/util.py