Metadata-Version: 1.0
Name: micromanager
Version: 0.1.13
Summary: Policy enforcement tool for GCP
Home-page: https://github.com/cleardataeng/micromanager
Author: Joe Ceresini
Author-email: UNKNOWN
License: Apache 2.0
Keywords: gcp policy enforcement
Platform: UNKNOWN
